README.rst
setup.py
menthol/__init__.py
menthol/__main__.py
menthol/benchmark.py
menthol/configuration.py
menthol/driver.py
menthol/util.py
menthol.egg-info/PKG-INFO
menthol.egg-info/SOURCES.txt
menthol.egg-info/dependency_links.txt
menthol.egg-info/entry_points.txt
menthol.egg-info/top_level.txt