Metadata-Version: 1.1
Name: menthol
Version: 0.0.2
Summary: A library that helps you exercising good benchmarking methodology
Home-page: https://github.com/caizixian/menthol
Author: Zixian Cai
Author-email: u5937495@anu.edu.au
License: Apache
Platform: UNKNOWN
Classifier: Development Status :: 3 - Alpha
Classifier: Intended Audience :: Science/Research
Classifier: License :: OSI Approved :: Apache Software License
Classifier: Topic :: System :: Benchmark
Classifier: Programming Language :: Python :: 3
